{"cameraMode":{"drawMode":0,"name":"Shaded","section":"Shading Mode"},"sceneLighting":true,"audioPlay":false,"sceneViewState":{"showFog":true,"showMaterialUpdate":false,"showSkybox":true,"showFlares":true,"showImageEffects":true,"showParticleSystems":true},"in2DMode":false,"pivot":{"x":4.465173244476318,"y":0.5916614532470703,"z":4.457015514373779},"rotation":{"x":-0.36439085006713869,"y":-0.17120584845542909,"z":0.06834360957145691,"w":-0.9128196239471436},"size":17.719207763671876,"orthographic":false}